{
  "fonts/EksellDisplayWeb-Medium.eot": "fonts/EksellDisplayWeb-Medium_15ac0ac8.eot",
  "fonts/EksellDisplayWeb-Medium.woff": "fonts/EksellDisplayWeb-Medium_65db42e3.woff",
  "fonts/EksellDisplayWeb-Medium.woff2": "fonts/EksellDisplayWeb-Medium_9dee04c0.woff2",
  "images/800px-Lonely_Planet.png": "images/800px-Lonely_Planet_d39d0214.png",
  "images/Plan-your-visit.png": "images/Plan-your-visit_1a2c497c.png",
  "images/Press-callouts.png": "images/Press-callouts_ba86f0c7.png",
  "images/Trip-Advisor-Logo.png": "images/Trip-Advisor-Logo_1a6eca31.png",
  "images/Yelp_trademark_RGB.png": "images/Yelp_trademark_RGB_7e097985.png",
  "images/Yelp_trademark_RGB_outline.png": "images/Yelp_trademark_RGB_outline_9f341356.png",
  "images/icon-close-white.svg": "images/icon-close-white_8b0dcdfe.svg",
  "images/icon-hamburger-white.svg": "images/icon-hamburger-white_c58e1ee0.svg",
  "images/mjh_logo_icon.svg": "images/mjh_logo_icon_ef5af421.svg",
  "images/placeholder.png": "images/placeholder_d9535082.png",
  "images/play-button.svg": "images/play-button_5a195121.svg",
  "images/tickets.svg": "images/tickets_796ea32d.svg",
  "images/time-out-new-york-logo.png": "images/time-out-new-york-logo_166d87b3.png",
  "images/yelp-logo-on-purple.png": "images/yelp-logo-on-purple_b61975b7.png",
  "images/young-friends.png": "images/young-friends_59c59877.png",
  "images/young-friends.svg": "images/young-friends_18ac559c.svg",
  "vendor/fontawesome-webfont.eot": "vendor/fontawesome-webfont_674f50d2.eot",
  "vendor/fontawesome-webfont.eot?v=4.7.0": "vendor/fontawesome-webfont_674f50d2.eot",
  "vendor/fontawesome-webfont.svg?v=4.7.0": "vendor/fontawesome-webfont_912ec66d.svg",
  "vendor/fontawesome-webfont.ttf?v=4.7.0": "vendor/fontawesome-webfont_b06871f2.ttf",
  "vendor/fontawesome-webfont.woff2?v=4.7.0": "vendor/fontawesome-webfont_af7ae505.woff2",
  "vendor/fontawesome-webfont.woff?v=4.7.0": "vendor/fontawesome-webfont_fee66e71.woff",
  "videos/auschwitz-intro.mp4": "videos/auschwitz-intro_238c9740.mp4",
  "scripts/customizer.js": "scripts/customizer_93a5f727.js",
  "styles/main.css": "styles/main_93a5f727.css",
  "scripts/main.js": "scripts/main_93a5f727.js"
}